fa_convnav/__init__.py
fa_convnav/_nbdev.py
fa_convnav/core.py
fa_convnav/examples00.py
fa_convnav/examples01.py
fa_convnav/models.py
fa_convnav/navigator.py
fa_convnav-0.0.2.dist-info/LICENSE
fa_convnav-0.0.2.dist-info/METADATA
fa_convnav-0.0.2.dist-info/WHEEL
fa_convnav-0.0.2.dist-info/entry_points.txt
fa_convnav-0.0.2.dist-info/top_level.txt
fa_convnav-0.0.2.dist-info/RECORD
