Metadata-Version: 2.1
Name: fa-convnav
Version: 0.0.2
Summary: CNN viewer
Home-page: https://github.com/hallmx/fa_convnav
Author: Mathew Hall
Author-email: mathew.hall100@gmail.com
License: Apache Software License 2.0
Keywords: fastai,CNN
Platform: UNKNOWN
Classifier: Development Status :: 3 - Alpha
Classifier: Intended Audience :: Developers
Classifier: License :: OSI Approved :: Apache Software License
Classifier: Natural Language :: English
Classifier: Programming Language :: Python :: 3.6
Classifier: Programming Language :: Python :: 3.7
Classifier: Programming Language :: Python :: 3.8
Requires-Python: >=3.6
